farmer/__init__.py
farmer/__main__.py
farmer/api.py
farmer/cli.py
farmer/config.py
farmer/logdna.py
farmer/messages.py
farmer/output.py
farmer/version.py
farmer/commands/__init__.py
farmer/commands/apps.py
farmer/commands/config.py
farmer/commands/deploy.py
farmer/commands/help.py
farmer/commands/logdna.py
farmer/commands/version.py
farmer-2.4.3.dist-info/LICENSE
farmer-2.4.3.dist-info/METADATA
farmer-2.4.3.dist-info/WHEEL
farmer-2.4.3.dist-info/entry_points.txt
farmer-2.4.3.dist-info/pbr.json
farmer-2.4.3.dist-info/top_level.txt
farmer-2.4.3.dist-info/RECORD
