Metadata-Version: 2.1
Name: farmer
Version: 2.4.3
Summary: Deploy your applications on VM Farms.
Home-page: https://github.com/vmfarms/farmer/
Author: VM Farms Inc.
Author-email: support@vmfarms.com
License: Apache 2.0
Platform: UNKNOWN
Classifier: Development Status :: 4 - Beta
Classifier: Intended Audience :: Developers
Classifier: License :: OSI Approved :: Apache Software License
Classifier: Programming Language :: Python :: 2.7
Classifier: Programming Language :: Python :: 3.4
Classifier: Programming Language :: Python :: 3.5
Classifier: Programming Language :: Python :: 3.6
Classifier: Programming Language :: Python :: 3.7
Requires-Dist: click (==6.6)
Requires-Dist: dateparser
Requires-Dist: layeredconfig (==0.3.2)
Requires-Dist: pytz
Requires-Dist: requests (>=2.20.0)
Requires-Dist: ruamel.yaml (>=0.15.70)
Requires-Dist: sh
Requires-Dist: six (>=1.11.0)
Requires-Dist: stevedore (>=1.2.0)
Requires-Dist: tzlocal
